pywaze/__init__.py
pywaze/route_calculator.py
pywaze-1.1.0.dist-info/METADATA
pywaze-1.1.0.dist-info/WHEEL
pywaze-1.1.0.dist-info/licenses/LICENSE
pywaze-1.1.0.dist-info/RECORD
