Metadata-Version: 2.3
Name: pywaze
Version: 1.1.0
Summary: Asynchronous Waze client for calculating routes and travel times.
Author-email: Kevin Stillhammer <kevin.stillhammer@gmail.com>
License-Expression: MIT
License-File: LICENSE
Classifier: License :: OSI Approved :: MIT License
Requires-Python: >=3.11
Requires-Dist: httpx>=0.27.0
